flux_ws_module/_flux_ws_module.pyd
flux_ws_module/_flux_ws_module.pyi
flux_ws_module/__init__.py
flux_ws_module-1.0.2.data/data/CMakeLists.txt
flux_ws_module-1.0.2.data/data/vcpkg.json
flux_ws_module-1.0.2.data/data/include/BaseExchangeConnector.h
flux_ws_module-1.0.2.data/data/include/CryptoExtensions.h
flux_ws_module-1.0.2.data/data/include/MexcConnector.h
flux_ws_module-1.0.2.data/data/include/OkxConnector.h
flux_ws_module-1.0.2.data/data/python_bindings/websocket_bindings.cpp
flux_ws_module-1.0.2.data/data/src/BaseExchangeConnector.cpp
flux_ws_module-1.0.2.data/data/src/CryptoExtensions.cpp
flux_ws_module-1.0.2.data/data/src/MexcConnector.cpp
flux_ws_module-1.0.2.data/data/src/OkxConnector.cpp
flux_ws_module-1.0.2.dist-info/DELVEWHEEL
flux_ws_module-1.0.2.dist-info/METADATA
flux_ws_module-1.0.2.dist-info/RECORD
flux_ws_module-1.0.2.dist-info/top_level.txt
flux_ws_module-1.0.2.dist-info/WHEEL
flux_ws_module.libs/libcrypto-3-x64-0f8e9202ff32aef6b88ab29a5f37cd86.dll
flux_ws_module.libs/libssl-3-x64-b4fed578b54e4001f0d9a8569b4e034f.dll
flux_ws_module.libs/msvcp140-436a5dde41a8c6923419ca7c22d158fc.dll
