Metadata-Version: 2.1
Name: flux_ws_module
Version: 1.0.2
Summary: Flux WS Module built with C++ and scikit-build
Author: Your Name
License: MIT
Requires-Python: >=3.8
Requires-Dist: pybind11>=2.10
